epaycosdk/__init__.py
epaycosdk/client.py
epaycosdk/epayco.py
epaycosdk/errors.py
epaycosdk/resources.py
epaycosdk/test/__init__.py
epaycosdk/utils/__init__.py
epaycosdk/utils/key_lang.json
epaycosdk/utils/key_langs.json
epaycosdk-3.0.3.dist-info/METADATA
epaycosdk-3.0.3.dist-info/WHEEL
epaycosdk-3.0.3.dist-info/top_level.txt
epaycosdk-3.0.3.dist-info/RECORD
